biasaway/BiasAway.py
biasaway/GC_compo_matching.py
biasaway/GC_window_compo_matching.py
biasaway/__init__.py
biasaway/altschulEriksonDinuclShuffle.py
biasaway/biasaway
biasaway/dinuc_shuffling_generator.py
biasaway/dinuc_window_shuffling_generator.py
biasaway/mononuc_shuffling_generator.py
biasaway/mononuc_window_shuffling_generator.py
biasaway/utils.py
biasaway-2.2.2.data/scripts/biasaway
biasaway-2.2.2.dist-info/LICENSE
biasaway-2.2.2.dist-info/METADATA
biasaway-2.2.2.dist-info/WHEEL
biasaway-2.2.2.dist-info/top_level.txt
biasaway-2.2.2.dist-info/RECORD
