Metadata-Version: 2.1
Name: biasaway
Version: 2.2.2
Summary: a tool to generate nucleotide composition-matched DNA sequences
Home-page: https://bitbucket.org/CBGR/biasaway/src/master/
Author: Anthony Mathelier and Aziz Khan
Author-email: anthony.mathelier@ncmm.uio.no
License: GPL
Platform: linux/unix
Classifier: Intended Audience :: Developers
Classifier: Intended Audience :: Science/Research
Classifier: License :: OSI Approved :: MIT License
Classifier: Operating System :: OS Independent
Classifier: Programming Language :: Python
Classifier: Programming Language :: Python :: 2.7
Classifier: Programming Language :: Python :: 3.4
Classifier: Programming Language :: Python :: 3.5
Classifier: Programming Language :: Python :: 3.6
Classifier: Topic :: Scientific/Engineering :: Bio-Informatics
Classifier: Topic :: Software Development :: Libraries :: Python Modules
Requires-Dist: biopython
Requires-Dist: numpy (==1.16.5)
Requires-Dist: matplotlib (==3.2.0)
Requires-Dist: seaborn
